pylexem/__init__.py
pylexem/lexer.py
pylexem/utils.py
pylexem-0.0.1.dist-info/LICENSE.md
pylexem-0.0.1.dist-info/METADATA
pylexem-0.0.1.dist-info/WHEEL
pylexem-0.0.1.dist-info/top_level.txt
pylexem-0.0.1.dist-info/RECORD
