Metadata-Version: 2.1
Name: pylexem
Version: 0.0.1
Summary: pylexem - python lexem analysis scanner tokenizer
Home-page: https://github.com/kr-g/pylexem
Author: k.r. goger
Author-email: k.r.goger+pylexem@gmail.com
License: UNKNOWN
Keywords: lex lexer lexem scanner tokenizer
Platform: UNKNOWN
Classifier: Development Status :: 3 - Alpha
Classifier: Operating System :: POSIX :: Linux
Classifier: Intended Audience :: Developers
Classifier: Programming Language :: Python :: 3
Classifier: License :: OSI Approved :: GNU Affero General Public License v3 or later (AGPLv3+)
Requires-Python: >=3.6
